LICENSE
MANIFEST.in
README.md
setup.cfg
setup.py
django_polybuilder.egg-info/PKG-INFO
django_polybuilder.egg-info/SOURCES.txt
django_polybuilder.egg-info/dependency_links.txt
django_polybuilder.egg-info/requires.txt
django_polybuilder.egg-info/top_level.txt
polybuilder/__init__.py
polybuilder/admin.py
polybuilder/apps.py
polybuilder/models.py
polybuilder/settings.py
polybuilder/tests.py
polybuilder/urls.py
polybuilder/utils.py
polybuilder/views.py
polybuilder/templates/_import.html
polybuilder/templates/base.html
polybuilder/templates/components.html
polybuilder/templates/dependencies.html
polybuilder/templates/index.html
polybuilder/templates/shared_components.html