Metadata-Version: 1.1
Name: django-polybuilder
Version: 0.2.2
Summary: Create your own Web Components from Django admin.
Home-page: https://sunetraalex@bitbucket.org/sparsy/django-polybuilder
Author: Sparsy
Author-email: sparsyteam@gmail.com
License: MIT License
Download-URL: https://bitbucket.org/sparsy/django-polybuilder/get/v_0.2.2.zip
Keywords: django,polymer,admin,editor,webcomponents
Platform: UNKNOWN
Classifier: Environment :: Web Environment
Classifier: Framework :: Django
Classifier: Intended Audience :: Developers
Classifier: License :: OSI Approved :: MIT License
Classifier: Operating System :: OS Independent
Classifier: Programming Language :: Python
Classifier: Programming Language :: Python :: 3.4
Classifier: Programming Language :: Python :: 3.5
Classifier: Programming Language :: Python :: 2.7
Classifier: Topic :: Internet :: WWW/HTTP
Classifier: Topic :: Internet :: WWW/HTTP :: Dynamic Content
